{"is_source_file": true, "format": "Python", "description": "This is an __init__.py file for the API package, primarily serving to set up the package and possibly import or initialize components related to the FastAPI app and routers.", "external_files": [], "external_methods": [], "published": [], "classes": [], "methods": [], "calls": [], "search-terms": ["__init__.py", "API package", "FastAPI", "routers"], "state": 2, "file_id": 2, "knowledge_revision": 17, "git_revision": "e276f290a7a1e1c72aa405cd2ef68fac5e1185c9", "revision_history": [{"6": "0da49343f4091606ee411c242858f1d9b9a022fa"}, {"17": "e276f290a7a1e1c72aa405cd2ef68fac5e1185c9"}], "ctags": [], "hash": "69c63f5f98f1c6babbebac687f73f30e", "format-version": 4, "code-base-name": "defect_management_backend", "filename": "defect_management_backend/src/api/__init__.py"}